nvstatsrecorder/__init__.py
nvstatsrecorder/callbacks.py
nvstatsrecorder/recorders.py
nvstatsrecorder-0.0.12.dist-info/LICENSE
nvstatsrecorder-0.0.12.dist-info/METADATA
nvstatsrecorder-0.0.12.dist-info/WHEEL
nvstatsrecorder-0.0.12.dist-info/top_level.txt
nvstatsrecorder-0.0.12.dist-info/RECORD
