Metadata-Version: 2.1
Name: nvstatsrecorder
Version: 0.0.12
Summary: NVStatsRecorder
Home-page: https://github.com/tlkh/NVStatsRecorder
Author: Timothy Liu
Author-email: tlkh.xms@gmail.com
License: UNKNOWN
Platform: UNKNOWN
Classifier: Programming Language :: Python :: 3
Classifier: License :: OSI Approved :: Apache Software License
Classifier: Operating System :: POSIX :: Linux
Classifier: Topic :: Scientific/Engineering :: Artificial Intelligence
Requires-Python: >=3.6
Requires-Dist: psutil
Requires-Dist: pynvml
Requires-Dist: py3nvml
Requires-Dist: matplotlib
Requires-Dist: numpy
